zockchinCrypto/__init__.py
zockchinCrypto/zockchinCrypto.py
zockchincrypto-0.1.2.dist-info/METADATA
zockchincrypto-0.1.2.dist-info/WHEEL
zockchincrypto-0.1.2.dist-info/top_level.txt
zockchincrypto-0.1.2.dist-info/RECORD
