Metadata-Version: 2.4
Name: zockchinCrypto
Version: 0.1.2
Summary: A Python library for various encryption algorithms including Fernet, Vigenère, Caesar, and Replacement ciphers.
Author: zyad mahmoud saad
Author-email: zyadmahmoud3993@gmail.com
Classifier: Programming Language :: Python :: 3
Classifier: License :: OSI Approved :: MIT License
Classifier: Operating System :: OS Independent
Classifier: Topic :: Security :: Cryptography
Requires-Python: >=3.6
Requires-Dist: cryptography
Dynamic: author
Dynamic: author-email
Dynamic: classifier
Dynamic: description
Dynamic: description-content-type
Dynamic: requires-dist
Dynamic: requires-python
Dynamic: summary
